pylibopus/__init__.py
pylibopus/api/__init__.py
pylibopus/api/ctl.py
pylibopus/api/decoder.py
pylibopus/api/encoder.py
pylibopus/api/info.py
pylibopus/api/multistream_decoder.py
pylibopus/api/multistream_encoder.py
pylibopus/api/projection_decoder.py
pylibopus/api/projection_encoder.py
pylibopus/classes.py
pylibopus/constants.py
pylibopus/exceptions.py
pylibopus-0.1.0.dist-info/LICENSE
pylibopus-0.1.0.dist-info/METADATA
pylibopus-0.1.0.dist-info/WHEEL
pylibopus-0.1.0.dist-info/entry_points.txt
pylibopus-0.1.0.dist-info/RECORD
