Metadata-Version: 2.1
Name: pylibopus
Version: 0.1.0
Summary: 
Author: alma
Author-email: alma.lindborg@gmail.com
Requires-Python: >=3.10,<4.0
Classifier: Programming Language :: Python :: 3
Classifier: Programming Language :: Python :: 3.10
Classifier: Programming Language :: Python :: 3.11
Classifier: Programming Language :: Python :: 3.12
Requires-Dist: flake8 (>=7.1.1,<8.0.0)
Requires-Dist: mypy (>=1.14.1,<2.0.0)
Requires-Dist: pylint (>=3.3.3,<4.0.0)
Requires-Dist: twine (>=6.1.0,<7.0.0)
